auto_ria_client/__init__.py
auto_ria_client/client.py
auto_ria_client/constants.py
auto_ria_client/enums.py
auto_ria_client/errors.py
auto_ria_client/search.py
auto_ria_python-0.0.2.dist-info/LICENSE
auto_ria_python-0.0.2.dist-info/METADATA
auto_ria_python-0.0.2.dist-info/WHEEL
auto_ria_python-0.0.2.dist-info/top_level.txt
auto_ria_python-0.0.2.dist-info/RECORD
